{
    "$kind": "Microsoft.AdaptiveDialog",
    "$designer": {
      "createdAt": "2019-07-04T08:14:01.139Z",
      "updatedAt": "2019-08-01T23:45:38.308Z",
      "id": "288769",
      "description": "This is a bot that demonstrates how to manage a ToDo list using regular expressions."
    },
    "autoEndDialog": false,
    "recognizer": {
      "$kind": "Microsoft.RegexRecognizer",
      "intents": [
        {

            "$kind": "Microsoft.IntentPattern",
            "intent": "AddIntent",
            "pattern": "(?i)(?:add|create) .*(?:to-do|todo|task)(?: )?(?:named (?<title>.*))?"
        },
        {

            "$kind": "Microsoft.IntentPattern",
            "intent": "ClearIntent",
            "pattern": "(?i)(?:delete|remove|clear) (?:all|every) (?:to-dos|todos|tasks)"
        },
        {

            "$kind": "Microsoft.IntentPattern",
            "intent": "DeleteIntent",
            "pattern": "(?i)(?:delete|remove|clear) .*(?:to-do|todo|task)(?: )?(?:named (?<title>.*))?"
        },
        {

            "$kind": "Microsoft.IntentPattern",
            "intent": "ShowIntent",
            "pattern": "(?i)(?:show|see|view) .*(?:to-do|todo|task)"
        },
        {

            "$kind": "Microsoft.IntentPattern",
            "intent": "HelpIntent",
            "pattern": "(?i)help"
        },
        {

            "$kind": "Microsoft.IntentPattern",
            "intent": "CancelIntent",
            "pattern": "(?i)cancel|never mind"
        }
    ]
    },
    "generator": "common.lg",
    "triggers": [
      {
        "$kind": "Microsoft.OnConversationUpdateActivity",
        "$designer": {
          "createdAt": "2019-07-01T22:02:14.960Z",
          "updatedAt": "2019-07-16T20:00:24.788Z",
          "id": "376720"
        },
        "constraint": "toLower(turn.Activity.membersAdded[0].name) != 'bot'",
        "actions": [
          {
            "$kind": "Microsoft.SendActivity",
            "$designer": {
              "createdAt": "2019-08-02T22:18:56.943Z",
              "updatedAt": "2019-08-02T22:36:20.947Z",
              "id": "157674"
            },
            "activity": "[SendActivity_157674]"
          }
        ]
      },
      {
        "$kind": "Microsoft.OnIntent",
        "$designer": {
          "createdAt": "2019-07-16T19:59:32.772Z",
          "updatedAt": "2019-07-16T19:59:36.277Z",
          "id": "064505"
        },
        "actions": [
          {
            "$kind": "Microsoft.BeginDialog",
            "dialog": "AddToDo"
          }
        ],
        "intent": "AddIntent"
      },
      {
        "$kind": "Microsoft.OnIntent",
        "$designer": {
          "createdAt": "2019-07-16T19:59:37.184Z",
          "updatedAt": "2019-08-01T23:46:50.759Z",
          "id": "114961"
        },
        "actions": [
          {
            "$kind": "Microsoft.BeginDialog",
            "dialog": "DeleteToDo",
            "$designer": {
              "createdAt": "2019-08-01T23:47:15.255Z",
              "updatedAt": "2019-08-01T23:47:15.258Z",
              "id": "978613"
            }
          }
        ],
        "intent": "DeleteIntent"
      },
      {
        "$kind": "Microsoft.OnIntent",
        "$designer": {
          "createdAt": "2019-07-16T19:59:41.352Z",
          "updatedAt": "2019-07-16T19:59:44.427Z",
          "id": "088050"
        },
        "actions": [
          {
            "$kind": "Microsoft.BeginDialog",
            "dialog": "ClearToDos"
          }
        ],
        "intent": "ClearIntent"
      },
      {
        "$kind": "Microsoft.OnIntent",
        "$designer": {
          "createdAt": "2019-07-16T19:59:50.315Z",
          "updatedAt": "2019-07-16T19:59:54.774Z",
          "id": "633942"
        },
        "actions": [
          {
            "$kind": "Microsoft.SendActivity",
            "$designer": {
              "createdAt": "2019-08-01T23:44:56.704Z",
              "updatedAt": "2019-08-01T23:44:57.629Z",
              "id": "696707"
            },
            "activity": "[SendActivity_696707]"
          }
        ],
        "intent": "HelpIntent"
      },
      {
        "$kind": "Microsoft.OnIntent",
        "$designer": {
          "createdAt": "2019-07-16T20:00:00.082Z",
          "updatedAt": "2019-07-16T20:00:03.344Z",
          "id": "794124"
        },
        "actions": [
          {
            "$kind": "Microsoft.BeginDialog",
            "dialog": "ShowToDos"
          }
        ],
        "intent": "ShowIntent"
      },
      {
        "$kind": "Microsoft.OnIntent",
        "$designer": {
          "createdAt": "2019-07-16T20:00:08.499Z",
          "updatedAt": "2019-07-16T20:00:12.504Z",
          "id": "179728"
        },
        "actions": [
          {
            "$kind": "Microsoft.SendActivity",
            "activity": "ok."
          },
          {
            "$kind": "Microsoft.EndDialog"
          }
        ],
        "intent": "CancelIntent"
      },
      {
        "$kind": "Microsoft.OnUnknownIntent",
        "$designer": {
          "createdAt": "2019-07-16T20:00:13.577Z",
          "updatedAt": "2019-07-16T20:00:19.435Z",
          "id": "677447"
        },
        "actions": [
          {
            "$kind": "Microsoft.SendActivity",
            "activity": "Hi! I'm a ToDo bot. Say \"add a todo named first\" to get started."
          }
        ]
      }
    ],
    "$schema": "../../app.schema"
  }
